AUTHORS
CHANGELOG.rst
LICENSE
MANIFEST.in
README.rst
setup.py
src/django_fab_templates/__init__.py
src/django_fab_templates/pastertemplates.py
src/django_fab_templates.egg-info/PKG-INFO
src/django_fab_templates.egg-info/SOURCES.txt
src/django_fab_templates.egg-info/dependency_links.txt
src/django_fab_templates.egg-info/entry_points.txt
src/django_fab_templates.egg-info/not-zip-safe
src/django_fab_templates.egg-info/requires.txt
src/django_fab_templates.egg-info/top_level.txt
src/django_fab_templates/templates/.DS_Store
src/django_fab_templates/templates/vagrant_project/.DS_Store
src/django_fab_templates/templates/vagrant_project/Vagrantfile
src/django_fab_templates/templates/vagrant_project/fabfile.py_tmpl
src/django_fab_templates/templates/vagrant_project/requirements.txt
src/django_fab_templates/templates/vagrant_project/+project+/.DS_Store
src/django_fab_templates/templates/vagrant_project/+project+/__init__.py
src/django_fab_templates/templates/vagrant_project/+project+/manage.py
src/django_fab_templates/templates/vagrant_project/+project+/settings.py_tmpl
src/django_fab_templates/templates/vagrant_project/+project+/urls.py
src/django_fab_templates/templates/vagrant_project/+project+/views.py
src/django_fab_templates/templates/vagrant_project/+project+/common/.DS_Store
src/django_fab_templates/templates/vagrant_project/+project+/common/__init__.py
src/django_fab_templates/templates/vagrant_project/+project+/common/admin.py
src/django_fab_templates/templates/vagrant_project/+project+/common/models.py
src/django_fab_templates/templates/vagrant_project/+project+/common/tests.py
src/django_fab_templates/templates/vagrant_project/+project+/common/migrations/.DS_Store
src/django_fab_templates/templates/vagrant_project/+project+/common/migrations/__init__.py
src/django_fab_templates/templates/vagrant_project/+project+/config/.DS_Store
src/django_fab_templates/templates/vagrant_project/+project+/config/__init__.py
src/django_fab_templates/templates/vagrant_project/+project+/config/vagrant.py_tmpl
src/django_fab_templates/templates/vagrant_project/+project+/media/.DS_Store
src/django_fab_templates/templates/vagrant_project/+project+/media/apple-touch-icon-114x114-precomposed.png
src/django_fab_templates/templates/vagrant_project/+project+/media/apple-touch-icon-57x57-precomposed.png
