Metadata-Version: 1.0
Name: django-fab-templates
Version: 0.1.2
Summary: Django project templates that support fabric-style deployment (vagrant+ubuntu, webfaction)
Home-page: https://github.com/dreamiurg/django-fab-templates
Author: Dmitry Guyvoronsky
Author-email: dmitry.guyvoronsky@gmail.com
License: MIT
Keywords: django,fabric,vagrant,template,project,html5,boilerplate,vm,virtualbox,paster
Platform: UNKNOWN
Classifier: Programming Language :: Python
Classifier: Development Status :: 3 - Alpha
Classifier: Environment :: Console
Classifier: Framework :: Django
Classifier: Intended Audience :: Developers
Classifier: License :: OSI Approved :: MIT License
Classifier: Operating System :: OS Independent
Classifier: Topic :: Software Development :: Libraries :: Python Modules
Classifier: Topic :: Software Development :: Code Generators
